[
  {
    "Episode":"Episode 1",
    "Server1":"https://lvturbo.com/gnzue4w52g1x.html",
    "Server2":"https://dooood.com/e/o8shy1zltw9z",
    "Server3":"https://streamtape.com/e/a2gbY7XMeDSQ8D/Episode_1.mp4"
  },{
    "Episode":"Episode 2",
    "Server1":"https://lvturbo.com/ntszcoeft70p.html",
    "Server2":"https://dooood.com/e/t1vm7rdcg8tj",
    "Server3":"https://streamtape.com/e/doqXJgLMmwFkRyx/Episode_2.mp4"
  },{
    "Episode":"Episode 3",
    "Server1":"https://lvturbo.com/o7er68lflmy4.html",
    "Server2":"https://dooood.com/e/ozrbc4peztg2",
    "Server3":"https://streamtape.com/e/o9bqrglmgXFKdw/Episode_3.mp4"
  },{
    "Episode":"Episode 4",
    "Server1":"https://lvturbo.com/9kf2wguaocjv.html",
    "Server2":"https://dooood.com/e/lns1ctd4gnpw",
    "Server3":"https://streamlare.com/e/ARPonQ3mZGxzb1aE"
  },{
    "Episode":"Episode 5",
    "Server1":"https://lvturbo.com/hpalb3tdpmo3.html",
    "Server2":"https://dooood.com/e/hsoif9ubxs2o",
    "Server3":"https://streamtape.com/e/YK6owG7w7GfvYlr/Episode_5.mp4"
  },{
    "Episode":"Episode 6",
    "Server1":"https://lvturbo.com/lnjnspquxn3t.html",
    "Server2":"https://dooood.com/e/hdq0kau3hqki",
    "Server3":"https://streamlare.com/e/LvgezwvPWANDbp8E"
  },{
    "Episode":"Episode 7",
    "Server1":"https://lvturbo.com/xvy4688mn7cc.html",
    "Server2":"https://dooood.com/e/7fs4u45ldzkx",
    "Server3":"https://streamlare.com/e/Jj8GzOqyvvMnvPog"
  },{
    "Episode":"Episode 8",
    "Server1":"https://lvturbo.com/oqtaol17l8pw.html",
    "Server2":"https://dooood.com/e/our30npd0eeq",
    "Server3":"https://streamlare.com/e/gLXEDVM91oJnQY74"
  },{
    "Episode":"Episode 9",
    "Server1":"https://lvturbo.com/rjinvihbai9j.html",
    "Server2":"https://dooood.com/e/801ij0itqeyv",
    "Server3":"https://streamtape.com/e/03xMZl2qG0IK6l/Episode_9.mp4"
  },{
    "Episode":"Episode 10",
    "Server1":"https://lvturbo.com/6b26buvwls8k.html",
    "Server2":"https://dooood.com/e/myrhqji13u7x",
    "Server3":"https://streamtape.com/e/Qe0JgrkVZViRPJ/Episode_10.mp4"
  },{
    "Episode":"Episode 11",
    "Server1":"",
    "Server2":"",
    "Server3":""
  },{
    "Episode":"Episode 12",
    "Server1":"",
    "Server2":"",
    "Server3":""
  }
]